{
  "stocks": [
    {
      "ticker": "JCTECH",
      "name": "JC科技集团",
      "sector": "科技",
      "ipo_price": 50.00,
      "current_price": 125.50,
      "market_cap": 25000000000,
      "volatility": 0.025,
      "description": "领先的科技创新公司，专注于人工智能、云计算和大数据解决方案",
      "pe_ratio": 28.5,
      "beta": 1.35,
      "dividend_yield": 0.0,
      "eps": 4.40,
      "book_value": 18.75,
      "debt_to_equity": 0.25,
      "rsi": 65.2,
      "moving_avg_50": 118.30,
      "moving_avg_200": 105.80,
      "year_high": 142.75,
      "year_low": 88.20,
      "ytd_return": 0.185
    },
    {
      "ticker": "JCBANK",
      "name": "JC银行",
      "sector": "金融",
      "ipo_price": 30.00,
      "current_price": 45.80,
      "market_cap": 18000000000,
      "volatility": 0.015,
      "description": "JCMarket最大的商业银行，提供全方位金融服务",
      "pe_ratio": 12.8,
      "beta": 0.85,
      "dividend_yield": 0.035,
      "eps": 3.58,
      "book_value": 28.90,
      "debt_to_equity": 8.5,
      "rsi": 52.1,
      "moving_avg_50": 44.25,
      "moving_avg_200": 42.10,
      "year_high": 48.95,
      "year_low": 38.75,
      "ytd_return": 0.095
    },
    {
      "ticker": "JCPHARMA",
      "name": "JC制药",
      "sector": "医药",
      "ipo_price": 80.00,
      "current_price": 156.20,
      "market_cap": 12000000000,
      "volatility": 0.020,
      "description": "创新药物研发和生产企业，在生物技术领域处于领先地位",
      "pe_ratio": 22.4,
      "beta": 0.95,
      "dividend_yield": 0.018,
      "eps": 6.97,
      "book_value": 32.15,
      "debt_to_equity": 0.35,
      "rsi": 58.7,
      "moving_avg_50": 148.60,
      "moving_avg_200": 135.40,
      "year_high": 168.90,
      "year_low": 118.50,
      "ytd_return": 0.142
    },
    {
      "ticker": "JCENERGY",
      "name": "JC能源",
      "sector": "能源",
      "ipo_price": 25.00,
      "current_price": 32.15,
      "market_cap": 8000000000,
      "volatility": 0.030,
      "description": "综合性能源公司，业务涵盖石油、天然气和可再生能源",
      "pe_ratio": 15.2,
      "beta": 1.25,
      "dividend_yield": 0.045,
      "eps": 2.11,
      "book_value": 24.80,
      "debt_to_equity": 1.2,
      "rsi": 48.3,
      "moving_avg_50": 30.85,
      "moving_avg_200": 28.95,
      "year_high": 38.75,
      "year_low": 22.40,
      "ytd_return": 0.068
    },
    {
      "ticker": "JCRETAIL",
      "name": "JC零售",
      "sector": "消费",
      "ipo_price": 40.00,
      "current_price": 68.90,
      "market_cap": 15000000000,
      "volatility": 0.018,
      "description": "大型零售连锁企业，线上线下一体化运营模式",
      "pe_ratio": 18.7,
      "beta": 1.05,
      "dividend_yield": 0.025,
      "eps": 3.68,
      "book_value": 22.40,
      "debt_to_equity": 0.65,
      "rsi": 61.4,
      "moving_avg_50": 65.20,
      "moving_avg_200": 58.75,
      "year_high": 74.85,
      "year_low": 52.30,
      "ytd_return": 0.125
    },
    {
      "ticker": "JCAUTO",
      "name": "JC汽车",
      "sector": "工业",
      "ipo_price": 60.00,
      "current_price": 89.75,
      "market_cap": 20000000000,
      "volatility": 0.022,
      "description": "新能源汽车制造商，智能驾驶技术的先驱者",
      "pe_ratio": 35.8,
      "beta": 1.45,
      "dividend_yield": 0.0,
      "eps": 2.51,
      "book_value": 15.90,
      "debt_to_equity": 0.45,
      "rsi": 72.1,
      "moving_avg_50": 82.40,
      "moving_avg_200": 75.60,
      "year_high": 95.20,
      "year_low": 58.75,
      "ytd_return": 0.235
    },
    {
      "ticker": "JCREAL",
      "name": "JC地产",
      "sector": "房地产",
      "ipo_price": 35.00,
      "current_price": 28.60,
      "market_cap": 6000000000,
      "volatility": 0.025,
      "description": "大型房地产开发企业，专注于住宅和商业地产开发",
      "pe_ratio": 8.5,
      "beta": 1.15,
      "dividend_yield": 0.055,
      "eps": 3.36,
      "book_value": 45.20,
      "debt_to_equity": 2.8,
      "rsi": 35.7,
      "moving_avg_50": 30.15,
      "moving_avg_200": 32.80,
      "year_high": 38.90,
      "year_low": 26.45,
      "ytd_return": -0.085
    },
    {
      "ticker": "JCFOOD",
      "name": "JC食品",
      "sector": "消费",
      "ipo_price": 20.00,
      "current_price": 38.45,
      "market_cap": 5000000000,
      "volatility": 0.016,
      "description": "知名食品饮料生产企业，拥有多个知名品牌",
      "pe_ratio": 16.2,
      "beta": 0.75,
      "dividend_yield": 0.032,
      "eps": 2.37,
      "book_value": 19.80,
      "debt_to_equity": 0.55,
      "rsi": 55.8,
      "moving_avg_50": 36.90,
      "moving_avg_200": 34.25,
      "year_high": 41.20,
      "year_low": 31.85,
      "ytd_return": 0.078
    },
    {
      "ticker": "JCMEDIA",
      "name": "JC传媒",
      "sector": "科技",
      "ipo_price": 45.00,
      "current_price": 72.30,
      "market_cap": 8000000000,
      "volatility": 0.028,
      "description": "数字媒体和娱乐内容提供商，在流媒体领域占据重要地位",
      "pe_ratio": 24.1,
      "beta": 1.25,
      "dividend_yield": 0.0,
      "eps": 3.00,
      "book_value": 16.50,
      "debt_to_equity": 0.35,
      "rsi": 68.5,
      "moving_avg_50": 68.75,
      "moving_avg_200": 62.40,
      "year_high": 78.90,
      "year_low": 48.20,
      "ytd_return": 0.165
    },
    {
      "ticker": "JCLOGIS",
      "name": "JC物流",
      "sector": "工业",
      "ipo_price": 30.00,
      "current_price": 52.80,
      "market_cap": 7000000000,
      "volatility": 0.020,
      "description": "现代化物流服务企业，智能仓储和配送网络覆盖全国",
      "pe_ratio": 19.5,
      "beta": 1.10,
      "dividend_yield": 0.028,
      "eps": 2.71,
      "book_value": 18.60,
      "debt_to_equity": 0.75,
      "rsi": 59.2,
      "moving_avg_50": 50.15,
      "moving_avg_200": 46.80,
      "year_high": 56.40,
      "year_low": 42.30,
      "ytd_return": 0.115
    },
    {
      "ticker": "JCINSURE",
      "name": "JC保险",
      "sector": "金融",
      "ipo_price": 25.00,
      "current_price": 41.25,
      "market_cap": 9000000000,
      "volatility": 0.014,
      "description": "综合性保险公司，提供人寿、财产和健康保险服务",
      "pe_ratio": 14.5,
      "beta": 0.90,
      "dividend_yield": 0.038,
      "eps": 2.84,
      "book_value": 26.70,
      "debt_to_equity": 0.45,
      "rsi": 56.3,
      "moving_avg_50": 39.80,
      "moving_avg_200": 37.25,
      "year_high": 43.90,
      "year_low": 33.15,
      "ytd_return": 0.105
    },
    {
      "ticker": "JCMINING",
      "name": "JC矿业",
      "sector": "能源",
      "ipo_price": 40.00,
      "current_price": 35.90,
      "market_cap": 4000000000,
      "volatility": 0.035,
      "description": "大型矿业公司，主要开采铁矿石、铜矿和稀土元素",
      "pe_ratio": 11.2,
      "beta": 1.55,
      "dividend_yield": 0.042,
      "eps": 3.21,
      "book_value": 28.40,
      "debt_to_equity": 1.1,
      "rsi": 42.8,
      "moving_avg_50": 37.60,
      "moving_avg_200": 39.85,
      "year_high": 45.20,
      "year_low": 31.75,
      "ytd_return": -0.065
    },
    {
      "ticker": "JCGAME",
      "name": "JC游戏",
      "sector": "科技",
      "ipo_price": 55.00,
      "current_price": 98.60,
      "market_cap": 6000000000,
      "volatility": 0.032,
      "description": "移动游戏开发和发行商，多款游戏在全球市场表现优异",
      "pe_ratio": 32.9,
      "beta": 1.40,
      "dividend_yield": 0.0,
      "eps": 2.99,
      "book_value": 12.80,
      "debt_to_equity": 0.15,
      "rsi": 75.6,
      "moving_avg_50": 89.25,
      "moving_avg_200": 78.40,
      "year_high": 105.30,
      "year_low": 62.85,
      "ytd_return": 0.285
    },
    {
      "ticker": "JCHOTEL",
      "name": "JC酒店",
      "sector": "消费",
      "ipo_price": 35.00,
      "current_price": 29.75,
      "market_cap": 3000000000,
      "volatility": 0.024,
      "description": "高端酒店连锁集团，在主要城市拥有豪华酒店物业",
      "pe_ratio": 9.8,
      "beta": 1.30,
      "dividend_yield": 0.048,
      "eps": 3.04,
      "book_value": 38.90,
      "debt_to_equity": 1.8,
      "rsi": 38.2,
      "moving_avg_50": 31.40,
      "moving_avg_200": 33.65,
      "year_high": 37.80,
      "year_low": 27.20,
      "ytd_return": -0.125
    },
    {
      "ticker": "JCAIR",
      "name": "JC航空",
      "sector": "工业",
      "ipo_price": 50.00,
      "current_price": 42.10,
      "market_cap": 5000000000,
      "volatility": 0.028,
      "description": "国内领先的航空公司，国内外航线网络完善",
      "pe_ratio": 13.7,
      "beta": 1.20,
      "dividend_yield": 0.022,
      "eps": 3.07,
      "book_value": 32.50,
      "debt_to_equity": 2.2,
      "rsi": 45.9,
      "moving_avg_50": 44.85,
      "moving_avg_200": 47.20,
      "year_high": 52.40,
      "year_low": 38.90,
      "ytd_return": -0.095
    },
    {
      "ticker": "JCBIO",
      "name": "JC生物",
      "sector": "医药",
      "ipo_price": 70.00,
      "current_price": 134.80,
      "market_cap": 4000000000,
      "volatility": 0.026,
      "description": "生物技术研发公司，专注于基因治疗和精准医疗",
      "pe_ratio": 45.2,
      "beta": 1.15,
      "dividend_yield": 0.0,
      "eps": 2.98,
      "book_value": 14.60,
      "debt_to_equity": 0.20,
      "rsi": 71.8,
      "moving_avg_50": 125.40,
      "moving_avg_200": 112.30,
      "year_high": 148.90,
      "year_low": 95.20,
      "ytd_return": 0.195
    },
    {
      "ticker": "JCSEMI",
      "name": "JC半导体",
      "sector": "科技",
      "ipo_price": 90.00,
      "current_price": 178.50,
      "market_cap": 15000000000,
      "volatility": 0.030,
      "description": "半导体芯片设计和制造企业，在AI芯片领域技术领先",
      "pe_ratio": 38.7,
      "beta": 1.50,
      "dividend_yield": 0.0,
      "eps": 4.61,
      "book_value": 22.40,
      "debt_to_equity": 0.30,
      "rsi": 78.2,
      "moving_avg_50": 165.80,
      "moving_avg_200": 148.60,
      "year_high": 195.40,
      "year_low": 125.30,
      "ytd_return": 0.245
    },
    {
      "ticker": "JCGREEN",
      "name": "JC新能源",
      "sector": "能源",
      "ipo_price": 45.00,
      "current_price": 67.20,
      "market_cap": 8000000000,
      "volatility": 0.025,
      "description": "可再生能源开发商，太阳能和风能项目遍布全国",
      "pe_ratio": 26.8,
      "beta": 1.35,
      "dividend_yield": 0.015,
      "eps": 2.51,
      "book_value": 19.80,
      "debt_to_equity": 0.85,
      "rsi": 63.4,
      "moving_avg_50": 62.90,
      "moving_avg_200": 56.40,
      "year_high": 72.80,
      "year_low": 48.60,
      "ytd_return": 0.155
    },
    {
      "ticker": "JCWATER",
      "name": "JC水务",
      "sector": "公用事业",
      "ipo_price": 20.00,
      "current_price": 26.85,
      "market_cap": 3000000000,
      "volatility": 0.012,
      "description": "城市供水和污水处理服务提供商，环保技术先进",
      "pe_ratio": 12.1,
      "beta": 0.65,
      "dividend_yield": 0.055,
      "eps": 2.22,
      "book_value": 18.90,
      "debt_to_equity": 0.95,
      "rsi": 54.7,
      "moving_avg_50": 25.80,
      "moving_avg_200": 24.60,
      "year_high": 28.40,
      "year_low": 22.15,
      "ytd_return": 0.085
    },
    {
      "ticker": "JCSPORT",
      "name": "JC体育",
      "sector": "消费",
      "ipo_price": 30.00,
      "current_price": 48.90,
      "market_cap": 2000000000,
      "volatility": 0.022,
      "description": "体育用品制造和体育赛事运营企业，品牌影响力强",
      "pe_ratio": 21.3,
      "beta": 1.10,
      "dividend_yield": 0.020,
      "eps": 2.30,
      "book_value": 16.40,
      "debt_to_equity": 0.50,
      "rsi": 64.1,
      "moving_avg_50": 46.25,
      "moving_avg_200": 42.80,
      "year_high": 52.70,
      "year_low": 38.15,
      "ytd_return": 0.135
    }
  ],
  "market_info": {
    "name": "JCMarket",
    "currency": "JCC",
    "trading_hours": {
      "open": "09:30",
      "close": "15:00",
      "timezone": "JCT"
    },
    "market_cap_total": 200000000000,
    "daily_volume_avg": 5000000000,
    "listed_companies": 20
  },
  "sectors": {
    "科技": {
      "description": "科技创新企业，包括软件、硬件、互联网等",
      "companies": ["JCTECH", "JCMEDIA", "JCGAME", "JCSEMI"],
      "market_cap_percentage": 27.0
    },
    "金融": {
      "description": "银行、保险、证券等金融服务企业",
      "companies": ["JCBANK", "JCINSURE"],
      "market_cap_percentage": 13.5
    },
    "医药": {
      "description": "制药、生物技术、医疗设备企业",
      "companies": ["JCPHARMA", "JCBIO"],
      "market_cap_percentage": 8.0
    },
    "能源": {
      "description": "传统能源和新能源企业",
      "companies": ["JCENERGY", "JCMINING", "JCGREEN"],
      "market_cap_percentage": 10.0
    },
    "消费": {
      "description": "零售、食品、酒店、体育等消费类企业",
      "companies": ["JCRETAIL", "JCFOOD", "JCHOTEL", "JCSPORT"],
      "market_cap_percentage": 12.5
    },
    "工业": {
      "description": "制造业、物流、航空等工业企业",
      "companies": ["JCAUTO", "JCLOGIS", "JCAIR"],
      "market_cap_percentage": 16.0
    },
    "房地产": {
      "description": "房地产开发和投资企业",
      "companies": ["JCREAL"],
      "market_cap_percentage": 3.0
    },
    "公用事业": {
      "description": "水务、电力、燃气等公用事业企业",
      "companies": ["JCWATER"],
      "market_cap_percentage": 1.5
    }
  },
  "indices": {
    "JC100": {
      "name": "JCMarket 100指数",
      "description": "JCMarket最具代表性的100只股票组成的指数",
      "base_value": 1000,
      "current_value": 2850.75
    },
    "JCTECH": {
      "name": "JC科技指数",
      "description": "科技行业股票组成的指数",
      "base_value": 1000,
      "current_value": 3420.60
    }
  }
}